pccl/__init__.py
pccl/_cdecls.py
pccl/_cuda.py
pccl/_loader.py
pccl/_pccl.py
pccl/_version.py
pccl/libpccl.dylib
pccl/master.py
pypccl-1.0.0.dist-info/METADATA
pypccl-1.0.0.dist-info/WHEEL
pypccl-1.0.0.dist-info/entry_points.txt
pypccl-1.0.0.dist-info/top_level.txt
pypccl-1.0.0.dist-info/RECORD
