Metadata-Version: 2.4
Name: pypccl
Version: 1.0.0
Summary: Fault tolerant Collective Communications over IP
Home-page: https://github.com/PrimeIntellect-ai/pccl
Author: Michael Keiblinger
Author-email: mike@primeintellect.ai, mario@primeintellect.ai
Project-URL: Bug Tracker, https://github.com/PrimeIntellect-ai/pccl/issues
Classifier: Programming Language :: Python :: 3
Classifier: Programming Language :: Python :: 3.12
Classifier: Programming Language :: Python :: 3.13
Classifier: Programming Language :: Python :: 3.14
Classifier: Operating System :: OS Independent
Classifier: Topic :: Software Development :: Libraries
Classifier: Topic :: System :: Distributed Computing
Requires-Dist: cffi
Requires-Dist: ipaddress
Requires-Dist: pycparser
Dynamic: author
Dynamic: description
Dynamic: requires-dist
Dynamic: summary
